{"nodes": [{"id": "arsa2526_event_brandbook_guidelines_12_full_collaterals_list", "label": "Full Event Collaterals List", "file_type": "image", "source_file": "docs/branding/[ARSA2526] Event Brandbook Guidelines/12.png", "source_location": null, "source_url": null, "captured_at": null, "author": null, "contributor": null}, {"id": "arsa2526_event_brandbook_guidelines_12_online_physical_video_photo_calendar_outputs", "label": "Online, Physical, Video, Photo, and Calendar Outputs", "file_type": "concept", "source_file": "docs/branding/[ARSA2526] Event Brandbook Guidelines/12.png", "source_location": null, "source_url": null, "captured_at": null, "author": null, "contributor": null}], "edges": [{"source": "arsa2526_event_brandbook_guidelines_12_full_collaterals_list", "target": "arsa2526_event_brandbook_guidelines_12_online_physical_video_photo_calendar_outputs", "relation": "references", "confidence": "EXTRACTED", "confidence_score": 1.0, "source_file": "docs/branding/[ARSA2526] Event Brandbook Guidelines/12.png", "source_location": null, "weight": 1.0}, {"source": "arsa2526_event_brandbook_guidelines_12_full_collaterals_list", "target": "arsa2526_event_brandbook_guidelines_3_event_output_planning", "relation": "conceptually_related_to", "confidence": "EXTRACTED", "confidence_score": 1.0, "source_file": "docs/branding/[ARSA2526] Event Brandbook Guidelines/12.png", "source_location": null, "weight": 1.0}], "hyperedges": []}